ducklake_delta_exporter/__init__.py
ducklake_delta_exporter-0.1.4.dist-info/METADATA
ducklake_delta_exporter-0.1.4.dist-info/WHEEL
ducklake_delta_exporter-0.1.4.dist-info/top_level.txt
ducklake_delta_exporter-0.1.4.dist-info/RECORD
