Metadata-Version: 2.4
Name: ducklake-delta-exporter
Version: 0.1.4
Summary: A utility to export DuckLake database metadata to Delta Lake transaction logs.
Home-page: https://github.com/djouallah/ducklake_delta_exporter
Author: mim
Author-email: your.email@example.com
Classifier: Programming Language :: Python :: 3
Classifier: License :: OSI Approved :: MIT License
Classifier: Operating System :: OS Independent
Classifier: Intended Audience :: Developers
Classifier: Topic :: Software Development :: Libraries :: Python Modules
Classifier: Development Status :: 3 - Alpha
Requires-Python: >=3.8
Requires-Dist: duckdb
Dynamic: author
Dynamic: author-email
Dynamic: classifier
Dynamic: description
Dynamic: description-content-type
Dynamic: home-page
Dynamic: requires-dist
Dynamic: requires-python
Dynamic: summary
